setup.py
ssh_utils.py
ssh_utils.egg-info/PKG-INFO
ssh_utils.egg-info/SOURCES.txt
ssh_utils.egg-info/dependency_links.txt
ssh_utils.egg-info/requires.txt
ssh_utils.egg-info/top_level.txt