Metadata-Version: 2.1
Name: ssh-utils
Version: 0.1
Summary: Utility library for managing SSH connections
Home-page: https://github.com/nithyavv/ssh-utils
Author: Nithya V
Author-email: nithya_v@dell.com
